subitokit/__init__.py
subitokit/main.py
subitokit-0.1.1.dist-info/METADATA
subitokit-0.1.1.dist-info/WHEEL
subitokit-0.1.1.dist-info/RECORD
