Metadata-Version: 2.1
Name: subitokit
Version: 0.1.1
Summary: Python module searcher for subito.it
Author: LucaSforza
Author-email: lucasforza1234@icloud.com
Requires-Python: >=3.10,<4.0
Classifier: Programming Language :: Python :: 3
Classifier: Programming Language :: Python :: 3.10
Classifier: Programming Language :: Python :: 3.11
Requires-Dist: bs4 (>=0.0.1,<0.0.2)
Requires-Dist: requests (>=2.28.2,<3.0.0)
